SimpleCLI/__init__.py
SimpleCLI/core.py
simple_cli_otus-0.0.0.dist-info/licenses/LICENSE
simple_cli_otus-0.0.0.dist-info/METADATA
simple_cli_otus-0.0.0.dist-info/WHEEL
simple_cli_otus-0.0.0.dist-info/top_level.txt
simple_cli_otus-0.0.0.dist-info/RECORD
