Metadata-Version: 2.4
Name: simple-cli-otus
Version: 0.0.0
Summary: Asynchronous CLI framework with command routing and advanced prompt features.
Author-email: Gabriel <datreallystupidmartis@gmail.com>
License: MIT
Classifier: Development Status :: 3 - Alpha
Classifier: Intended Audience :: Developers
Classifier: License :: OSI Approved :: MIT License
Classifier: Programming Language :: Python :: 3.8
Classifier: Programming Language :: Python :: 3.9
Classifier: Programming Language :: Python :: 3.10
Classifier: Programming Language :: Python :: 3.11
Classifier: Operating System :: POSIX :: Linux
Classifier: Topic :: Software Development :: Libraries :: Application Frameworks
Classifier: Topic :: Terminals
Requires-Python: >=3.8
License-File: LICENSE
Requires-Dist: pydantic<3,>=1.10
Requires-Dist: typing-extensions>=4.0
Provides-Extra: dev
Requires-Dist: black>=23.3; extra == "dev"
Requires-Dist: mypy>=1.3; extra == "dev"
Requires-Dist: pytest>=7.3; extra == "dev"
Requires-Dist: pytest-asyncio>=0.21; extra == "dev"
Dynamic: license-file
